asedftk/__init__.py
asedftk/juliatests.jl
asedftk/precompile.jl
asedftk/run_calculation.jl
asedftk/test_ase_default_calculator_tests.py
asedftk/test_juliatests.py
asedftk/test_registering.py
asedftk/test_silicon.py
asedftk/dftk_environment/Project.toml
asedftk-0.2.7.dist-info/LICENSE
asedftk-0.2.7.dist-info/METADATA
asedftk-0.2.7.dist-info/WHEEL
asedftk-0.2.7.dist-info/top_level.txt
asedftk-0.2.7.dist-info/RECORD
