Metadata-Version: 2.1
Name: asedftk
Version: 0.2.7
Summary: DFTK-based calculator for ASE
Home-page: https://github.com/mfherbst/asedftk
Author: Michael F. Herbst
Author-email: info@michael-herbst.com
License: MIT
Keywords: density-functional,theory,DFT,computational,chemistry,quantum,materials,science,electronic,structure,ab-initio,pseudopotential,analysis,ASE,DFTK
Platform: UNKNOWN
Classifier: Development Status :: 4 - Beta
Classifier: License :: OSI Approved :: MIT License
Classifier: Programming Language :: Python :: 3.6
Classifier: Programming Language :: Python :: 3.7
Classifier: Programming Language :: Python :: 3.8
Classifier: Topic :: Scientific/Engineering :: Mathematics
Classifier: Topic :: Scientific/Engineering :: Physics
Classifier: Topic :: Scientific/Engineering :: Chemistry
Requires-Python: >=3.6
Requires-Dist: ase (>=3)
Requires-Dist: numpy (>=1.14)
